attributes_doc/__init__.py
attributes_doc/_base.py
attributes_doc/py.typed
attributes_doc-0.3.0.dist-info/LICENSE
attributes_doc-0.3.0.dist-info/METADATA
attributes_doc-0.3.0.dist-info/WHEEL
attributes_doc-0.3.0.dist-info/top_level.txt
attributes_doc-0.3.0.dist-info/RECORD
