Metadata-Version: 2.1
Name: attributes-doc
Version: 0.3.0
Summary: PEP 224 implementation
Home-page: https://github.com/tkukushkin/attributes-doc
Author: Timofey Kukushkin
Author-email: tima@kukushkin.me
License: MIT
Project-URL: Source, https://github.com/tkukushkin/attributes-doc
Platform: UNKNOWN
Classifier: Development Status :: 4 - Beta
Classifier: Intended Audience :: Developers
Classifier: License :: OSI Approved :: MIT License
Classifier: Operating System :: OS Independent
Classifier: Programming Language :: Python :: 2
Classifier: Programming Language :: Python :: 2.7
Classifier: Programming Language :: Python :: 3
Classifier: Programming Language :: Python :: 3.6
Classifier: Programming Language :: Python :: 3.7
Classifier: Programming Language :: Python :: 3.8
Classifier: Programming Language :: Python :: 3.9
Classifier: Programming Language :: Python :: 3.10
Classifier: Topic :: Software Development :: Libraries :: Python Modules
License-File: LICENSE
Requires-Dist: typing ; python_version < "3"
